sqd/__init__.py
sqd/_compat.py
sqd/dataset.py
sqd/models.py
sqd/py.typed
sqd/sqd.py
sqd/transport.py
sqd/utils.py
sqd/query/__init__.py
sqd/query/base_query.py
sqd/query/cursor.py
sqd/query/progress.py
sqd/query/evm/__init__.py
sqd/query/evm/decode.py
sqd/query/evm/fields.py
sqd/query/evm/query.py
sqd/query/evm/requests.py
sqd/query/solana/__init__.py
sqd/query/solana/fields.py
sqd/query/solana/query.py
sqd/query/solana/requests.py
sqd_py-0.1.8.dist-info/METADATA
sqd_py-0.1.8.dist-info/WHEEL
sqd_py-0.1.8.dist-info/licenses/LICENSE
sqd_py-0.1.8.dist-info/RECORD
