Metadata-Version: 2.4
Name: sqd_py
Version: 0.1.8
Summary: Lightweight Python client for querying blockchain data from SQD Network
Project-URL: Homepage, https://sqd.ai
Project-URL: Documentation, https://docs.sqd.dev
Project-URL: Repository, https://github.com/subsquid/sqd-portal-client-py
Project-URL: Issues, https://github.com/subsquid/sqd-portal-client-py/issues
Project-URL: Changelog, https://github.com/subsquid/sqd-portal-client-py/blob/main/CHANGELOG.md
Author-email: Anton Bernatskiy <abernatskiy@toha.li>, Evgeny Shestakov <evgeny.shestakov.0x@gmail.com>
Maintainer: Subsquid Labs
License-Expression: MIT
License-File: LICENSE
Keywords: async,blockchain,data,ethereum,evm,indexer,solana,sqd,subsquid,web3
Classifier: Development Status :: 4 - Beta
Classifier: Framework :: AsyncIO
Classifier: Intended Audience :: Developers
Classifier: License :: OSI Approved :: MIT License
Classifier: Operating System :: OS Independent
Classifier: Programming Language :: Python :: 3
Classifier: Programming Language :: Python :: 3.10
Classifier: Programming Language :: Python :: 3.11
Classifier: Programming Language :: Python :: 3.12
Classifier: Programming Language :: Python :: 3.13
Classifier: Topic :: Internet
Classifier: Topic :: Software Development :: Libraries :: Python Modules
Classifier: Typing :: Typed
Requires-Python: >=3.10
Requires-Dist: aiohttp>=3.9.0
Requires-Dist: tqdm>=4.67.1
Requires-Dist: ujson>=5.11.0
Provides-Extra: dev
Requires-Dist: mypy>=1.10.0; extra == 'dev'
Requires-Dist: pytest-asyncio>=0.23.0; extra == 'dev'
Requires-Dist: pytest-mock>=3.10.0; extra == 'dev'
Requires-Dist: pytest>=8.0.0; extra == 'dev'
Requires-Dist: ruff>=0.4.0; extra == 'dev'
Requires-Dist: types-tqdm>=4.66.0; extra == 'dev'
